py4knn/__init__.py
py4knn/distance.py
py4knn/k_nearest_neighbors.py
py4knn-0.0.5.dist-info/METADATA
py4knn-0.0.5.dist-info/WHEEL
py4knn-0.0.5.dist-info/top_level.txt
py4knn-0.0.5.dist-info/RECORD
